captur_ml/__init__.py
captur_ml/base.py
captur_ml/core/__init__.py
captur_ml/core/dtypes/__init__.py
captur_ml/core/dtypes/data.py
captur_ml/core/dtypes/generic.py
captur_ml/core/dtypes/image.py
captur_ml/core/dtypes/label.py
captur_ml/core/dtypes/prediction.py
captur_ml/core/dtypes/result.py
captur_ml/core/dtypes/parsers/__init__.py
captur_ml/core/dtypes/parsers/parse_request.py
captur_ml/core/entities/__init__.py
captur_ml/core/entities/endpoint/__init__.py
captur_ml/core/entities/endpoint/base.py
captur_ml/core/entities/endpoint/vertexai.py
captur_ml/core/entities/storage_folder/__init__.py
captur_ml/core/entities/storage_folder/base.py
captur_ml/core/entities/storage_folder/gcs.py
captur_ml/core/exceptions/__init__.py
captur_ml/core/services/__init__.py
captur_ml/core/services/aiplatform/__init__.py
captur_ml/core/services/aiplatform/batch_predict/__init__.py
captur_ml/core/services/aiplatform/dataset/__init__.py
captur_ml/core/services/aiplatform/live_predict/__init__.py
captur_ml/core/services/aiplatform/model_train/__init__.py
captur_ml/core/services/gcs/__init__.py
captur_ml/core/services/pubsub/__init__.py
captur_ml/core/services/reporting/__init__.py
captur_ml/core/utils/__init__.py
captur_ml/core/utils/image/__init__.py
captur_ml/core/utils/parse/__init__.py
captur_ml/core/utils/parse/utils.py
captur_ml/core/utils/path/__init__.py
captur_ml/evaluate/__init__.py
captur_ml/evaluate/dataset.py
captur_ml/evaluate/evaluate.py
captur_ml/evaluate/metrics.py
captur_ml/predict/__init__.py
captur_ml/predict/batch.py
captur_ml/predict/live.py
captur_ml/webhooks/__init__.py
captur_ml-0.3.1.dist-info/LICENCE.md
captur_ml-0.3.1.dist-info/METADATA
captur_ml-0.3.1.dist-info/WHEEL
captur_ml-0.3.1.dist-info/top_level.txt
captur_ml-0.3.1.dist-info/RECORD
