Metadata-Version: 2.1
Name: captur-ml
Version: 0.3.1
Summary: The internal Captur Machine Learning SDK
Home-page: https://github.com/Captur/captur-ml-sdk
Author: ['Jack Barnett Leveson', 'Jonny Jackson', 'Shrinivasan Sankar']
Author-email: jack@captur.ai
License: Creative Commons Attribution-NonCommercial-NoDerivatives 4.0 International
Platform: UNKNOWN
Classifier: Intended Audience :: Developers
Classifier: License :: OSI Approved :: BSD License
Classifier: Operating System :: POSIX :: Linux
Classifier: Programming Language :: Python :: 3
Classifier: Programming Language :: Python :: 3.10
Requires-Python: >=3.10
License-File: LICENCE.md
Requires-Dist: pydantic
Requires-Dist: google-cloud-storage
Requires-Dist: google-cloud-aiplatform
Requires-Dist: google-cloud-pubsub
Requires-Dist: google-auth
Requires-Dist: Pillow
Requires-Dist: regex
Requires-Dist: dataclasses-json
Requires-Dist: numpy
